README.rst
setup.py
metacash/__init__.py
metacash/account.py
metacash/configuration.py
metacash/labels.py
metacash/log.py
metacash/meta.py
metacash/metacash.py
metacash/transactions.py
metacash/version.py
metacash.egg-info/PKG-INFO
metacash.egg-info/SOURCES.txt
metacash.egg-info/dependency_links.txt
metacash.egg-info/requires.txt
metacash.egg-info/top_level.txt
metacash/dashboards/__init__.py
metacash/dashboards/account_overview.py
metacash/dashboards/category_analysis.py
metacash/dashboards/dashboard_widget.py
metacash/dashboards/plots.py
metacash/dashboards/select_transactions.py
metacash/dashboards/utils.py
metacash/readers/__init__.py
metacash/readers/inbank.py
metacash/readers/inbank_operator.py
metacash/readers/metacash.py
metacash/readers/paypal.py
metacash/simulation/__init__.py
metacash/simulation/sim_transactions.py